mcp_sentry/__init__.py
mcp_sentry/__main__.py
mcp_sentry/server.py
mcp_sentry-0.6.2.dist-info/METADATA
mcp_sentry-0.6.2.dist-info/WHEEL
mcp_sentry-0.6.2.dist-info/entry_points.txt
mcp_sentry-0.6.2.dist-info/RECORD
