Metadata-Version: 2.4
Name: mcp-sentry
Version: 0.6.2
Summary: MCP server for retrieving issues from sentry.io
Requires-Python: >=3.10
Requires-Dist: mcp>=1.0.0
